demix/__init__.py
demix/cli.py
demix/py.typed
demix-1.3.0.dist-info/LICENSE
demix-1.3.0.dist-info/METADATA
demix-1.3.0.dist-info/WHEEL
demix-1.3.0.dist-info/entry_points.txt
demix-1.3.0.dist-info/top_level.txt
demix-1.3.0.dist-info/RECORD
