Metadata-Version: 2.1
Name: demix
Version: 1.3.0
Summary: Separate audio into stems (vocals, instruments) using AI-powered Spleeter
Author: pwittchen
License: Apache-2.0
Project-URL: Homepage, https://github.com/pwittchen/demix
Project-URL: Repository, https://github.com/pwittchen/demix
Project-URL: Issues, https://github.com/pwittchen/demix/issues
Keywords: audio,music,stem-separation,vocals,spleeter,youtube,ffmpeg
Classifier: Development Status :: 4 - Beta
Classifier: Environment :: Console
Classifier: Intended Audience :: End Users/Desktop
Classifier: Intended Audience :: Developers
Classifier: License :: OSI Approved :: Apache Software License
Classifier: Operating System :: OS Independent
Classifier: Programming Language :: Python :: 3
Classifier: Programming Language :: Python :: 3.8
Classifier: Topic :: Multimedia :: Sound/Audio
Classifier: Topic :: Multimedia :: Sound/Audio :: Analysis
Classifier: Topic :: Multimedia :: Sound/Audio :: Conversion
Requires-Python: <3.9,>=3.8
License-File: LICENSE
Requires-Dist: pytubefix>=9.3.0
Requires-Dist: ffmpeg>=1.4
Requires-Dist: spleeter>=2.3.2
Provides-Extra: dev
Requires-Dist: pytest>=7.0; extra == "dev"
Requires-Dist: flake8>=5.0; extra == "dev"
